{
    "enabled": true,
    "neededInstalledMods": [],
    "neededUninstalledMods": [],
    "spawns": [
        {
            "id": "infernape-3",
            "pokemon": "infernape",
            "type": "pokemon",
            "context": "grounded",
            "bucket": "uncommon",
            "level": "35-45",
            "weight": 250.0,
            "condition": {
                "canSeeSky": true,
                "timeRange": "day",
                "minX": 0,
                "minY": 80,
                "neededBaseBlocks": [
                    "minecraft:stone"
                ],
                "neededNearbyBlocks": [
                    "minecraft:moss_block",
                    "minecraft:hay_block"
                ],
                "biomes": [
                    "#cobblemon:is_mountain"
                ]
            },
            "anticondition": {
                "neededNearbyBlocks": [
                    "minecraft:water"
                ]
            }
        }
    ]
}