{
    "enabled": "true",
    "neededInstalledMods": [],
    "neededUninstalledMods": [],
    "spawns": [
        {
            "id": "pincurchin",
            "pokemon": "pincurchin",
            "presets": [
                "underwater"
            ],
            "type": "pokemon",
            "context": "seafloor",
            "bucket": "uncommon",
            "level": "20-40",
            "weight": 2.0,
            "condition": {
                "canSeeSky": true,
                "biomes": [
                    "#minecraft:is_beach"
                ]
            }
        }
    ]
}